rfc3230_digest_headers/__init__.py
rfc3230_digest_headers/exceptions.py
rfc3230_digest_headers/rfc3230.py
rfc3230_digest_headers-1.0.5.dist-info/METADATA
rfc3230_digest_headers-1.0.5.dist-info/WHEEL
rfc3230_digest_headers-1.0.5.dist-info/licenses/LICENSE
rfc3230_digest_headers-1.0.5.dist-info/RECORD
