Metadata-Version: 2.4
Name: rfc3230-digest-headers
Version: 1.0.5
Summary: Implementation of the Digest HTTP headers according to RFC 3230.
Project-URL: Repository, https://github.com/Mari6814/py-rfc3230-digest-headers
Project-URL: Documentation, https://github.com/Mari6814/py-rfc3230-digest-headers
Author-email: Marian Plivelic <marianplivelic@gmail.com>
License-Expression: MIT
License-File: LICENSE
Keywords: authentication,digest,headers,http,integrity,rfc3230,security
Classifier: Development Status :: 5 - Production/Stable
Classifier: License :: OSI Approved :: MIT License
Classifier: Operating System :: OS Independent
Classifier: Programming Language :: Python :: 3
Classifier: Programming Language :: Python :: 3.10
Classifier: Programming Language :: Python :: 3.11
Classifier: Programming Language :: Python :: 3.12
Classifier: Programming Language :: Python :: 3.13
Classifier: Programming Language :: Python :: 3.14
Classifier: Topic :: Internet :: WWW/HTTP
Classifier: Topic :: Security
Classifier: Topic :: Software Development :: Libraries
Requires-Python: >=3.10
